{
  "arch_packages": "mips_24kc",
  "build_at": "2020-09-16 13:55:54",
  "default_packages": [
    "base-files",
    "libc",
    "libgcc",
    "busybox",
    "dropbear",
    "mtd",
    "uci",
    "opkg",
    "netifd",
    "fstools",
    "uclient-fetch",
    "logd",
    "kmod-gpio-button-hotplug",
    "swconfig",
    "kmod-ath9k",
    "wpad-mini",
    "uboot-envtools",
    "dnsmasq",
    "iptables",
    "ip6tables",
    "ppp",
    "ppp-mod-pppoe",
    "firewall",
    "odhcpd-ipv6only",
    "odhcp6c",
    "kmod-gpio-button-hotplug",
    "swconfig",
    "kmod-ath9k",
    "wpad-mini",
    "uboot-envtools"
  ],
  "device_packages": [
    "kmod-usb-core",
    "kmod-usb2",
    "-uboot-envtools"
  ],
  "id": "rut900",
  "image_prefix": "openwrt-18.06.8-ar71xx-generic-rut900",
  "images": [
    {
      "name": "openwrt-18.06.8-ar71xx-generic-rut900-squashfs-factory.bin",
      "sha256": "6456d50ff5c63f63c22d97ab5851c88ac40f74f60288fa5cebcd4b1c307ab3b6",
      "type": "factory"
    },
    {
      "name": "openwrt-18.06.8-ar71xx-generic-rut900-squashfs-sysupgrade.bin",
      "sha256": "a751e36571b4d5e9742c11712d5fd5ee8a4c7b6feeaa6329cb5436875d22dbd9",
      "type": "sysupgrade"
    }
  ],
  "metadata_version": 1,
  "supported_devices": [
    "rut900"
  ],
  "target": "ar71xx/generic",
  "titles": [
    {
      "title": "Teltonika RUT900"
    }
  ],
  "version_code": "r7989-82fbd85747",
  "version_number": "18.06.8"
}