{
  "arch_packages": "mips_24kc",
  "build_at": "2020-09-16 13:55:54",
  "default_packages": [
    "base-files",
    "libc",
    "libgcc",
    "busybox",
    "dropbear",
    "mtd",
    "uci",
    "opkg",
    "netifd",
    "fstools",
    "uclient-fetch",
    "logd",
    "kmod-gpio-button-hotplug",
    "swconfig",
    "kmod-ath9k",
    "wpad-mini",
    "uboot-envtools",
    "dnsmasq",
    "iptables",
    "ip6tables",
    "ppp",
    "ppp-mod-pppoe",
    "firewall",
    "odhcpd-ipv6only",
    "odhcp6c",
    "kmod-gpio-button-hotplug",
    "swconfig",
    "kmod-ath9k",
    "wpad-mini",
    "uboot-envtools"
  ],
  "device_packages": [
    "kmod-usb-core",
    "kmod-usb2",
    "kmod-usb-storage"
  ],
  "id": "wrtnode2q",
  "image_prefix": "openwrt-18.06.8-ar71xx-generic-wrtnode2q",
  "images": [
    {
      "name": "openwrt-18.06.8-ar71xx-generic-wrtnode2q-squashfs-sysupgrade.bin",
      "sha256": "adbb97294cf2ea64c8df30a22f4e7e06707a025f70235c3d237f532d9172571d",
      "type": "sysupgrade"
    }
  ],
  "metadata_version": 1,
  "supported_devices": [],
  "target": "ar71xx/generic",
  "titles": [
    {
      "title": "WRTnode2Q"
    }
  ],
  "version_code": "r7989-82fbd85747",
  "version_number": "18.06.8"
}