{
  "arch_packages": "mipsel_24kc",
  "build_at": "2023-09-22 06:59:57",
  "default_packages": [
    "base-files",
    "busybox",
    "ca-bundle",
    "dnsmasq",
    "dropbear",
    "firewall4",
    "fstools",
    "kmod-gpio-button-hotplug",
    "kmod-leds-gpio",
    "kmod-nft-offload",
    "kmod-rt2800-soc",
    "libc",
    "libgcc",
    "libustream-wolfssl",
    "logd",
    "mtd",
    "netifd",
    "nftables",
    "odhcp6c",
    "odhcpd-ipv6only",
    "opkg",
    "ppp",
    "ppp-mod-pppoe",
    "procd",
    "procd-seccomp",
    "swconfig",
    "uci",
    "uclient-fetch",
    "urandom-seed",
    "urngd",
    "wpad-basic-wolfssl"
  ],
  "device_packages": [
    "kmod-usb2"
  ],
  "image_path": "22.03.5/targets/ramips/rt305x/",
  "image_prefix": "openwrt-22.03.5-ramips-rt305x-poray_m4-8m",
  "images": [
    {
      "filesystem": "initramfs",
      "name": "openwrt-22.03.5-ramips-rt305x-poray_m4-8m-initramfs-kernel.bin",
      "sha256": "5979994a70de197aed6d5652b4bec9f580297ff05fd78e0120bd000918c89c85",
      "sha256_unsigned": "5979994a70de197aed6d5652b4bec9f580297ff05fd78e0120bd000918c89c85",
      "type": "kernel"
    },
    {
      "filesystem": "squashfs",
      "name": "openwrt-22.03.5-ramips-rt305x-poray_m4-8m-squashfs-sysupgrade.bin",
      "sha256": "bb182a9c435fbd68676d4d994e3b851c351ec66d982f06622e92cebaa7348645",
      "sha256_unsigned": "3882b7a101ca57c6aa36a053f2c704385e25c7834e4de31e9e5ac14beee6244d",
      "type": "sysupgrade"
    },
    {
      "filesystem": "squashfs",
      "name": "openwrt-22.03.5-ramips-rt305x-poray_m4-8m-squashfs-factory.bin",
      "sha256": "48755f30f23368e540255cb091167b49cbe0d68675324c32b710af74c17af9c5",
      "sha256_unsigned": "48755f30f23368e540255cb091167b49cbe0d68675324c32b710af74c17af9c5",
      "type": "factory"
    }
  ],
  "metadata_version": 1,
  "model_id": "poray_m4-8m",
  "source_date_epoch": 1682627295,
  "supported_devices": [
    "poray,m4-8m",
    "m4-8M"
  ],
  "target": "ramips/rt305x",
  "titles": [
    {
      "model": "M4",
      "variant": "8M",
      "vendor": "Poray"
    }
  ],
  "version_code": "r20134-5f15225c1e",
  "version_number": "22.03.5"
}