{
  "arch_packages": "mipsel_24kc",
  "build_at": "2023-09-22 06:59:57",
  "default_packages": [
    "base-files",
    "busybox",
    "ca-bundle",
    "dnsmasq",
    "dropbear",
    "firewall4",
    "fstools",
    "kmod-gpio-button-hotplug",
    "kmod-leds-gpio",
    "kmod-mt7603",
    "kmod-nft-offload",
    "libc",
    "libgcc",
    "libustream-wolfssl",
    "logd",
    "mtd",
    "netifd",
    "nftables",
    "odhcp6c",
    "odhcpd-ipv6only",
    "opkg",
    "ppp",
    "ppp-mod-pppoe",
    "procd",
    "procd-seccomp",
    "procd-ujail",
    "swconfig",
    "uci",
    "uclient-fetch",
    "urandom-seed",
    "urngd",
    "wpad-basic-wolfssl"
  ],
  "device_packages": [
    "kmod-mt76x2"
  ],
  "image_path": "22.03.5/targets/ramips/mt76x8/",
  "image_prefix": "openwrt-22.03.5-ramips-mt76x8-netgear_r6080",
  "images": [
    {
      "filesystem": "initramfs",
      "name": "openwrt-22.03.5-ramips-mt76x8-netgear_r6080-initramfs-kernel.bin",
      "sha256": "172d058ec0e0d1f3e331387031f90316b63510b9203fa029825a62cbe7d596bc",
      "sha256_unsigned": "172d058ec0e0d1f3e331387031f90316b63510b9203fa029825a62cbe7d596bc",
      "type": "kernel"
    },
    {
      "filesystem": "squashfs",
      "name": "openwrt-22.03.5-ramips-mt76x8-netgear_r6080-squashfs-factory.img",
      "sha256": "b2038b4130b293b8372221ebd0ff761f53b6d6238ff62c0c62c6c85daa47ea27",
      "sha256_unsigned": "b2038b4130b293b8372221ebd0ff761f53b6d6238ff62c0c62c6c85daa47ea27",
      "type": "factory"
    },
    {
      "filesystem": "squashfs",
      "name": "openwrt-22.03.5-ramips-mt76x8-netgear_r6080-squashfs-sysupgrade.bin",
      "sha256": "212b30da192ae02ea408c59e94ec712fb74d00aec2d432864ebb392476041126",
      "sha256_unsigned": "713c9b591fc57d554fd7476fdc28d13fc035522862c90a0ea544d3523a4a7a77",
      "type": "sysupgrade"
    }
  ],
  "metadata_version": 1,
  "model_id": "netgear_r6080",
  "source_date_epoch": 1682627295,
  "supported_devices": [
    "netgear,r6080"
  ],
  "target": "ramips/mt76x8",
  "titles": [
    {
      "model": "R6080",
      "vendor": "NETGEAR"
    }
  ],
  "version_code": "r20134-5f15225c1e",
  "version_number": "22.03.5"
}