{
  "arch_packages": "mips_mips32",
  "build_at": "2020-09-16 13:55:53",
  "default_packages": [
    "base-files",
    "libc",
    "libgcc",
    "busybox",
    "dropbear",
    "mtd",
    "uci",
    "opkg",
    "netifd",
    "fstools",
    "uclient-fetch",
    "logd",
    "swconfig",
    "kmod-gpio-button-hotplug",
    "dnsmasq",
    "iptables",
    "ip6tables",
    "ppp",
    "ppp-mod-pppoe",
    "firewall",
    "odhcpd-ipv6only",
    "odhcp6c",
    "swconfig",
    "kmod-gpio-button-hotplug"
  ],
  "device_packages": [],
  "id": "96358VW2-generic",
  "image_prefix": "openwrt-18.06.8-brcm63xx-smp-96358VW2-generic",
  "images": [
    {
      "name": "openwrt-18.06.8-brcm63xx-smp-96358VW2-generic-squashfs-cfe.bin",
      "sha256": "95704ab16aa752ca420f709175ceb4b230be0206d9ce154278538a1a2340ae03",
      "type": "cfe"
    }
  ],
  "metadata_version": 1,
  "supported_devices": [],
  "target": "brcm63xx/smp",
  "titles": [
    {
      "title": "Generic 96358VW2"
    }
  ],
  "version_code": "r7989-82fbd85747",
  "version_number": "18.06.8"
}