{
  "arch_packages": "mips_mips32",
  "build_at": "2020-09-16 13:55:53",
  "default_packages": [
    "base-files",
    "libc",
    "libgcc",
    "busybox",
    "dropbear",
    "mtd",
    "uci",
    "opkg",
    "netifd",
    "fstools",
    "uclient-fetch",
    "logd",
    "swconfig",
    "kmod-gpio-button-hotplug",
    "dnsmasq",
    "iptables",
    "ip6tables",
    "ppp",
    "ppp-mod-pppoe",
    "firewall",
    "odhcpd-ipv6only",
    "odhcp6c",
    "swconfig",
    "kmod-gpio-button-hotplug"
  ],
  "device_packages": [
    "kmod-b43",
    "wpad-mini",
    "kmod-usb2",
    "kmod-usb-ohci",
    "kmod-usb-ledtrig-usbport",
    "iwinfo"
  ],
  "id": "DGND3700v1",
  "image_prefix": "openwrt-18.06.8-brcm63xx-generic-DGND3700v1",
  "images": [
    {
      "name": "openwrt-18.06.8-brcm63xx-generic-DGND3700v1-squashfs-sysupgrade.bin",
      "sha256": "5f1d628a4c345d10873031db72d7d49cc2191280bbf439a95453f736e6c970df",
      "type": "sysupgrade"
    },
    {
      "name": "openwrt-18.06.8-brcm63xx-generic-DGND3700v1-squashfs-factory.chk",
      "sha256": "3490c71e4eedc3a08636dc64747142a5bafa9df7737120b2c5e2f4d250e69a20",
      "type": "factory"
    }
  ],
  "metadata_version": 1,
  "supported_devices": [],
  "target": "brcm63xx/generic",
  "titles": [
    {
      "title": "Netgear DGND3700 v1"
    }
  ],
  "version_code": "r7989-82fbd85747",
  "version_number": "18.06.8"
}