{
  "arch_packages": "mips_24kc",
  "build_at": "2020-12-08 11:59:41",
  "default_packages": [
    "base-files",
    "libc",
    "libgcc",
    "busybox",
    "dropbear",
    "mtd",
    "uci",
    "opkg",
    "netifd",
    "fstools",
    "uclient-fetch",
    "logd",
    "urandom-seed",
    "urngd",
    "kmod-gpio-button-hotplug",
    "swconfig",
    "kmod-ath9k",
    "uboot-envtools",
    "wpad-basic",
    "dnsmasq",
    "iptables",
    "ip6tables",
    "ppp",
    "ppp-mod-pppoe",
    "firewall",
    "odhcpd-ipv6only",
    "odhcp6c",
    "kmod-ipt-offload",
    "kmod-gpio-button-hotplug",
    "swconfig",
    "kmod-ath9k",
    "uboot-envtools"
  ],
  "device_packages": ["kmod-usb-core", "kmod-usb2", "kmod-usb-ohci"],
  "id": "ubnt-air-gateway-pro",
  "image_prefix": "openwrt-19.07.5-ar71xx-generic-ubnt-air-gateway-pro",
  "images": [
    {
      "name": "openwrt-19.07.5-ar71xx-generic-ubnt-air-gateway-pro-squashfs-sysupgrade.bin",
      "sha256": "5b15962391ac26f8a6f7a552ced86f575701980daf11df96ce1170ec33354fb8",
      "type": "sysupgrade"
    },
    {
      "name": "openwrt-19.07.5-ar71xx-generic-ubnt-air-gateway-pro-squashfs-factory.bin",
      "sha256": "7400e0f7a3c7b2efdd5ee2f3f27c90d1067c48e9df4722a21e74791e1690fd0f",
      "type": "factory"
    }
  ],
  "metadata_version": 1,
  "supported_devices": [],
  "target": "ar71xx/generic",
  "titles": [{ "title": "Ubiquiti Air Gateway Pro" }],
  "version_code": "r11257-5090152ae3",
  "version_number": "19.07.5"
}
