{
  "arch_packages": "mips_24kc",
  "build_at": "2020-09-08 18:49:19",
  "default_packages": [
    "base-files",
    "libc",
    "libgcc",
    "busybox",
    "dropbear",
    "mtd",
    "uci",
    "opkg",
    "netifd",
    "fstools",
    "uclient-fetch",
    "logd",
    "urandom-seed",
    "urngd",
    "kmod-gpio-button-hotplug",
    "swconfig",
    "kmod-ath9k",
    "uboot-envtools",
    "wpad-basic",
    "dnsmasq",
    "iptables",
    "ip6tables",
    "ppp",
    "ppp-mod-pppoe",
    "firewall",
    "odhcpd-ipv6only",
    "odhcp6c",
    "kmod-ipt-offload",
    "kmod-gpio-button-hotplug",
    "swconfig",
    "kmod-ath9k",
    "uboot-envtools"
  ],
  "device_packages": [
    "kmod-ath10k-ct",
    "ath10k-firmware-qca99x0-ct"
  ],
  "id": "netgear_ex7300",
  "image_prefix": "openwrt-19.07.4-ath79-generic-netgear_ex7300",
  "images": [
    {
      "name": "openwrt-19.07.4-ath79-generic-netgear_ex7300-squashfs-sysupgrade.bin",
      "sha256": "892d9b328277c71e4774039bea3272986f20c43127ab212ed561c2bfbb87a345",
      "type": "sysupgrade"
    },
    {
      "name": "openwrt-19.07.4-ath79-generic-netgear_ex7300-squashfs-factory.img",
      "sha256": "a2d9bc76be316f22fdd8cad8a698a6ffa66aa9a0bf795a68505d2c187939f973",
      "type": "factory"
    }
  ],
  "metadata_version": 1,
  "supported_devices": [
    "netgear,ex7300"
  ],
  "target": "ath79/generic",
  "titles": [
    {
      "title": "NETGEAR EX7300"
    }
  ],
  "version_code": "r11208-ce6496d796",
  "version_number": "19.07.4"
}