{
  "id": "A226G",
  "image_prefix": "openwrt-brcm63xx-generic-A226G",
  "images": [
    {
      "name": "openwrt-brcm63xx-generic-A226G-squashfs-cfe.bin",
      "sha256": "fde043ca9e9f11d4fca4a09a4ec9f461e9d0fc6fc262b307a98f21b512370c18",
      "type": "cfe"
    }
  ],
  "metadata_version": 1,
  "supported_devices": [],
  "target": "brcm63xx/generic",
  "titles": [
    {
      "model": "A226G",
      "vendor": "Pirelli"
    }
  ],
  "version_commit": "r12145-4716c843d6",
  "version_number": "SNAPSHOT"
}