{
  "arch_packages": "arm_cortex-a8_vfpv3",
  "build_at": "2020-09-16 13:55:54",
  "default_packages": [
    "base-files",
    "libc",
    "libgcc",
    "busybox",
    "dropbear",
    "mtd",
    "uci",
    "opkg",
    "netifd",
    "fstools",
    "uclient-fetch",
    "logd",
    "dnsmasq",
    "iptables",
    "ip6tables",
    "ppp",
    "ppp-mod-pppoe",
    "firewall",
    "odhcpd-ipv6only",
    "odhcp6c",
    "kmod-ipt-offload"
  ],
  "device_packages": [],
  "id": "am335x-boneblack",
  "image_prefix": "openwrt-18.06.9-omap-am335x-boneblack",
  "images": [
    {
      "name": "openwrt-18.06.9-omap-am335x-boneblack-ubifs-sdcard.img.gz",
      "sha256": "387b766171d56b862f70fdd6ef098b9be4985384f937194282713562e4b556fa",
      "type": "sdcard"
    },
    {
      "name": "openwrt-18.06.9-omap-am335x-boneblack-ext4-sdcard.img.gz",
      "sha256": "a90b3b89bb88fb325166507de89cf43b3ed866655a27ca8d9748e5cc74b71e9e",
      "type": "sdcard"
    }
  ],
  "metadata_version": 1,
  "supported_devices": [
    "am335x-boneblack"
  ],
  "target": "omap/generic",
  "titles": [
    {
      "title": "TI AM335x BeagleBone Black"
    }
  ],
  "version_code": "r7989-82fbd85747",
  "version_number": "18.06.9"
}