{
  "arch_packages": "mipsel_24kc",
  "build_at": "2023-09-22 06:59:57",
  "default_packages": [
    "base-files",
    "libc",
    "libgcc",
    "busybox",
    "dropbear",
    "mtd",
    "uci",
    "opkg",
    "netifd",
    "fstools",
    "uclient-fetch",
    "logd",
    "urandom-seed",
    "urngd",
    "kmod-leds-gpio",
    "kmod-gpio-button-hotplug",
    "swconfig",
    "kmod-rt2800-soc",
    "wpad-mini",
    "dnsmasq",
    "iptables",
    "ip6tables",
    "ppp",
    "ppp-mod-pppoe",
    "firewall",
    "odhcpd-ipv6only",
    "odhcp6c",
    "kmod-ipt-offload",
    "kmod-leds-gpio",
    "kmod-gpio-button-hotplug",
    "swconfig"
  ],
  "device_packages": [
    "jboot-tools",
    "kmod-usb2",
    "kmod-spi-dev",
    "kmod-usb-serial",
    "kmod-usb-serial-option",
    "kmod-usb-net",
    "kmod-usb-net-cdc-ether",
    "comgt-ncm"
  ],
  "image_path": "releases/19.07.10/targets/ramips/rt305x/",
  "image_prefix": "openwrt-19.07.10-ramips-rt305x-dwr-512-b",
  "images": [
    {
      "filesystem": "squashfs",
      "name": "openwrt-19.07.10-ramips-rt305x-dwr-512-b-squashfs-factory.bin",
      "sha256": "2171de9e3215a2ebc388f52b0a47f289524615a53a59a3fd80202393e7ce5fc5",
      "type": "factory"
    },
    {
      "filesystem": "squashfs",
      "name": "openwrt-19.07.10-ramips-rt305x-dwr-512-b-squashfs-sysupgrade.bin",
      "sha256": "9f4baf80b6b2afeb64a365d24eb6cf05c9826e0ef3d62792d5ac5e77d669b309",
      "type": "sysupgrade"
    }
  ],
  "metadata_version": 1,
  "model_id": "dwr-512-b",
  "source_date_epoch": 1650114812,
  "supported_devices": [
    "dwr-512-b"
  ],
  "target": "ramips/rt305x",
  "titles": [
    {
      "title": "D-Link DWR-512 B"
    }
  ],
  "version_code": "r11427-9ce6aa9d8d",
  "version_number": "19.07.10"
}