{
  "arch_packages": "mipsel_24kc",
  "build_at": "2020-12-11 00:03:46",
  "default_packages": [
    "base-files",
    "ca-bundle",
    "dropbear",
    "fstools",
    "libc",
    "libgcc",
    "libustream-wolfssl",
    "logd",
    "mtd",
    "netifd",
    "opkg",
    "uci",
    "uclient-fetch",
    "urandom-seed",
    "urngd",
    "busybox",
    "procd",
    "kmod-leds-gpio",
    "kmod-gpio-button-hotplug",
    "wpad-basic-wolfssl",
    "dnsmasq",
    "firewall",
    "ip6tables",
    "iptables",
    "kmod-ipt-offload",
    "odhcp6c",
    "odhcpd-ipv6only",
    "ppp",
    "ppp-mod-pppoe",
    "kmod-leds-gpio",
    "kmod-gpio-button-hotplug"
  ],
  "device_packages": ["kmod-mt76x2", "kmod-usb3", "kmod-usb-ledtrig-usbport"],
  "id": "storylink_sap-g3200u3",
  "image_prefix": "openwrt-ramips-mt7621-storylink_sap-g3200u3",
  "images": [
    {
      "name": "openwrt-ramips-mt7621-storylink_sap-g3200u3-squashfs-sysupgrade.bin",
      "sha256": "51ae3dcad8aab86cf4650afb040cb7b67b8e525a7ac18d1677ea880370acbfab",
      "type": "sysupgrade"
    }
  ],
  "metadata_version": 1,
  "source_date_epoch": "1607628831",
  "supported_devices": ["storylink,sap-g3200u3", "sap-g3200u3"],
  "target": "ramips/mt7621",
  "titles": [{ "model": "SAP-G3200U3", "vendor": "STORYLiNK" }],
  "version_code": "r15182-8663072854",
  "version_number": "SNAPSHOT"
}
