{
  "id": "d-team_newifi-d2",
  "image_prefix": "openwrt-ramips-mt7621-d-team_newifi-d2",
  "images": [
    {
      "name": "openwrt-ramips-mt7621-d-team_newifi-d2-squashfs-sysupgrade.bin",
      "sha256": "de2fdd50829548c65c3947501f5822c8c034dc0105cae5af7af1f32404e21e0c",
      "type": "sysupgrade"
    }
  ],
  "metadata_version": 1,
  "supported_devices": [
    "d-team,newifi-d2"
  ],
  "target": "ramips/mt7621",
  "titles": [
    {
      "model": "D2",
      "vendor": "Newifi"
    }
  ],
  "version_commit": "r12138-1e3bfbafd3",
  "version_number": "SNAPSHOT"
}