{
  "id": "iodata_wn-gx300gr",
  "image_prefix": "openwrt-ramips-mt7621-iodata_wn-gx300gr",
  "images": [
    {
      "name": "openwrt-ramips-mt7621-iodata_wn-gx300gr-squashfs-sysupgrade.bin",
      "sha256": "00d994f986a83644cfa31085566aecf028165fac0bd0a4c628b8f1b699e806d7",
      "type": "sysupgrade"
    }
  ],
  "metadata_version": 1,
  "supported_devices": [
    "iodata,wn-gx300gr"
  ],
  "target": "ramips/mt7621",
  "titles": [
    {
      "model": "WN-GX300GR",
      "vendor": "I-O DATA"
    }
  ],
  "version_commit": "r12145-4716c843d6",
  "version_number": "SNAPSHOT"
}