{
  "arch_packages": "arm_arm1176jzf-s_vfp",
  "build_at": "2020-09-08 13:26:31",
  "default_packages": [
    "base-files",
    "libc",
    "libgcc",
    "busybox",
    "dropbear",
    "mtd",
    "uci",
    "opkg",
    "netifd",
    "fstools",
    "uclient-fetch",
    "logd",
    "urandom-seed",
    "urngd",
    "brcm2708-gpu-fw",
    "kmod-usb-hid",
    "kmod-sound-core",
    "kmod-sound-arm-bcm2835",
    "kmod-fs-vfat",
    "kmod-nls-cp437",
    "kmod-nls-iso8859-1",
    "partx-utils",
    "mkf2fs",
    "e2fsprogs",
    "dnsmasq",
    "iptables",
    "ip6tables",
    "ppp",
    "ppp-mod-pppoe",
    "firewall",
    "odhcpd-ipv6only",
    "odhcp6c",
    "kmod-ipt-offload",
    "brcm2708-gpu-fw",
    "kmod-usb-hid",
    "kmod-sound-core",
    "kmod-sound-arm-bcm2835",
    "kmod-fs-vfat",
    "kmod-nls-cp437",
    "kmod-nls-iso8859-1",
    "partx-utils",
    "mkf2fs",
    "e2fsprogs"
  ],
  "device_packages": [
    "brcmfmac-firmware-43430-sdio",
    "brcmfmac-board-rpi2",
    "kmod-brcmfmac",
    "wpad-basic",
    "iwinfo"
  ],
  "id": "rpi",
  "image_prefix": "openwrt-19.07.4-brcm2708-bcm2708-rpi",
  "images": [
    {
      "name": "openwrt-19.07.4-brcm2708-bcm2708-rpi-ext4-sysupgrade.img.gz",
      "sha256": "c7ea3abc317ad6f425062856170cb8448bbdbe7ff00c43ab06a5960bc8d15a05",
      "type": "sysupgrade"
    },
    {
      "name": "openwrt-19.07.4-brcm2708-bcm2708-rpi-squashfs-factory.img.gz",
      "sha256": "39138c6b7898ec88b77da7b77bd431f5279d724aaa9cda79cecbd135d12db74d",
      "type": "factory"
    },
    {
      "name": "openwrt-19.07.4-brcm2708-bcm2708-rpi-squashfs-sysupgrade.img.gz",
      "sha256": "f53dc49520e1b361b10f4bacee5587771ed4a5886e6e61e010125631a1a42004",
      "type": "sysupgrade"
    },
    {
      "name": "openwrt-19.07.4-brcm2708-bcm2708-rpi-ext4-factory.img.gz",
      "sha256": "2c269377abb155261c7b35305de7fec1e9b7132e73a615a62b68e2a0535d0eab",
      "type": "factory"
    }
  ],
  "metadata_version": 1,
  "supported_devices": [
    "rpi-b",
    "rpi-b-plus",
    "rpi-cm",
    "rpi-zero",
    "rpi-zero-w",
    "raspberrypi,model-b",
    "raspberrypi,model-b-plus",
    "raspberrypi,model-b-rev2",
    "raspberrypi,compute-module",
    "raspberrypi,compute-module-1",
    "raspberrypi,model-zero",
    "raspberrypi,model-zero-w"
  ],
  "target": "brcm2708/bcm2708",
  "titles": [
    {
      "title": "Raspberry Pi B/B+/CM/Zero/ZeroW"
    }
  ],
  "version_code": "r11208-ce6496d796",
  "version_number": "19.07.4"
}