{
  "arch_packages": "mipsel_24kc",
  "build_at": "2020-09-16 13:55:54",
  "default_packages": [
    "base-files",
    "libc",
    "libgcc",
    "busybox",
    "dropbear",
    "mtd",
    "uci",
    "opkg",
    "netifd",
    "fstools",
    "uclient-fetch",
    "logd",
    "kmod-leds-gpio",
    "kmod-gpio-button-hotplug",
    "swconfig",
    "dnsmasq",
    "iptables",
    "ip6tables",
    "ppp",
    "ppp-mod-pppoe",
    "firewall",
    "odhcpd-ipv6only",
    "odhcp6c",
    "kmod-ipt-offload",
    "kmod-leds-gpio",
    "kmod-gpio-button-hotplug",
    "swconfig"
  ],
  "device_packages": [],
  "id": "elecom_wrc-1167ghbk2-s",
  "image_prefix": "openwrt-18.06.8-ramips-mt7621-elecom_wrc-1167ghbk2-s",
  "images": [
    {
      "name": "openwrt-18.06.8-ramips-mt7621-elecom_wrc-1167ghbk2-s-squashfs-factory.bin",
      "sha256": "3ae083b1e0b3cf9d0c51587d83a2a7c4c72853f80961d5e6dcf167bdf12a8a8a",
      "type": "factory"
    },
    {
      "name": "openwrt-18.06.8-ramips-mt7621-elecom_wrc-1167ghbk2-s-squashfs-sysupgrade.bin",
      "sha256": "bacbe1dec71ff8b318079763bf17d726d08a01e14d3588e319f04e90787d90b2",
      "type": "sysupgrade"
    }
  ],
  "metadata_version": 1,
  "supported_devices": [
    "elecom,wrc-1167ghbk2-s"
  ],
  "target": "ramips/mt7621",
  "titles": [
    {
      "title": "ELECOM WRC-1167GHBK2-S"
    }
  ],
  "version_code": "r7989-82fbd85747",
  "version_number": "18.06.8"
}