{
  "id": "winchannel_wb2000",
  "image_prefix": "openwrt-ath79-generic-winchannel_wb2000",
  "images": [
    {
      "name": "openwrt-ath79-generic-winchannel_wb2000-squashfs-sysupgrade.bin",
      "sha256": "5c649915106c996e0ad632c215e02e6fa18fd3914913e1bc649dfac2e785f094",
      "type": "sysupgrade"
    }
  ],
  "metadata_version": 1,
  "supported_devices": [
    "winchannel,wb2000"
  ],
  "target": "ath79/generic",
  "titles": [
    {
      "model": "WB2000",
      "vendor": "Winchannel"
    }
  ],
  "version_commit": "r12145-4716c843d6",
  "version_number": "SNAPSHOT"
}