{
  "arch_packages": "mipsel_24kc",
  "build_at": "2020-12-11 15:51:38",
  "default_packages": [
    "base-files",
    "ca-bundle",
    "dropbear",
    "fstools",
    "libc",
    "libgcc",
    "libustream-wolfssl",
    "logd",
    "mtd",
    "netifd",
    "opkg",
    "uci",
    "uclient-fetch",
    "urandom-seed",
    "urngd",
    "busybox",
    "procd",
    "kmod-leds-gpio",
    "kmod-gpio-button-hotplug",
    "kmod-mt7603",
    "wpad-basic-wolfssl",
    "swconfig",
    "dnsmasq",
    "firewall",
    "ip6tables",
    "iptables",
    "kmod-ipt-offload",
    "odhcp6c",
    "odhcpd-ipv6only",
    "ppp",
    "ppp-mod-pppoe",
    "kmod-leds-gpio",
    "kmod-gpio-button-hotplug"
  ],
  "device_packages": ["kmod-mt76x2"],
  "id": "buffalo_wcr-1166ds",
  "image_prefix": "openwrt-ramips-mt76x8-buffalo_wcr-1166ds",
  "images": [
    {
      "name": "openwrt-ramips-mt76x8-buffalo_wcr-1166ds-squashfs-factory.bin",
      "sha256": "9e78e333dc4983c12795785b7f6c774722f3dbe1e0ad61ee1e95474d68a50cda",
      "type": "factory"
    },
    {
      "name": "openwrt-ramips-mt76x8-buffalo_wcr-1166ds-squashfs-sysupgrade.bin",
      "sha256": "b0945d4775581542fd6c5e7e7c3cdc4d32012192f977d21bf47b98b6661ecb83",
      "type": "sysupgrade"
    }
  ],
  "metadata_version": 1,
  "source_date_epoch": "1607691424",
  "supported_devices": ["buffalo,wcr-1166ds", "wcr-1166ds"],
  "target": "ramips/mt76x8",
  "titles": [{ "model": "WCR-1166DS", "vendor": "Buffalo" }],
  "version_code": "r15198-882ca13d92",
  "version_number": "SNAPSHOT"
}
