{
  "arch_packages": "mipsel_24kc",
  "build_at": "2020-12-11 15:51:38",
  "default_packages": [
    "base-files",
    "ca-bundle",
    "dropbear",
    "fstools",
    "libc",
    "libgcc",
    "libustream-wolfssl",
    "logd",
    "mtd",
    "netifd",
    "opkg",
    "uci",
    "uclient-fetch",
    "urandom-seed",
    "urngd",
    "busybox",
    "procd",
    "kmod-leds-gpio",
    "kmod-gpio-button-hotplug",
    "kmod-mt7603",
    "wpad-basic-wolfssl",
    "swconfig",
    "dnsmasq",
    "firewall",
    "ip6tables",
    "iptables",
    "kmod-ipt-offload",
    "odhcp6c",
    "odhcpd-ipv6only",
    "ppp",
    "ppp-mod-pppoe",
    "kmod-leds-gpio",
    "kmod-gpio-button-hotplug"
  ],
  "device_packages": [
    "kmod-usb2",
    "kmod-usb-ohci",
    "kmod-usb-ledtrig-usbport",
    "kmod-sdhci-mt7620"
  ],
  "id": "vocore_vocore2",
  "image_prefix": "openwrt-ramips-mt76x8-vocore_vocore2",
  "images": [
    {
      "name": "openwrt-ramips-mt76x8-vocore_vocore2-squashfs-sysupgrade.bin",
      "sha256": "3c3830b33a2405d822b2e0abe70e38f3e14e277e09d1008b08e6a0e9df6a85bb",
      "type": "sysupgrade"
    }
  ],
  "metadata_version": 1,
  "source_date_epoch": "1607691424",
  "supported_devices": ["vocore,vocore2", "vocore2"],
  "target": "ramips/mt76x8",
  "titles": [{ "model": "VoCore2", "vendor": "VoCore" }],
  "version_code": "r15198-882ca13d92",
  "version_number": "SNAPSHOT"
}
