{
  "arch_packages": "arm_cortex-a5_vfpv4",
  "build_at": "2020-09-08 14:12:42",
  "default_packages": [
    "base-files",
    "libc",
    "libgcc",
    "busybox",
    "dropbear",
    "mtd",
    "uci",
    "opkg",
    "netifd",
    "fstools",
    "uclient-fetch",
    "logd",
    "urandom-seed",
    "urngd",
    "kmod-usb-ohci",
    "kmod-at91-udc",
    "kmod-usb-gadget-eth",
    "kmod-usb2",
    "dnsmasq",
    "iptables",
    "ip6tables",
    "ppp",
    "ppp-mod-pppoe",
    "firewall",
    "odhcpd-ipv6only",
    "odhcp6c",
    "kmod-ipt-offload",
    "kmod-usb-ohci",
    "kmod-at91-udc",
    "kmod-usb-gadget-eth"
  ],
  "device_packages": [],
  "id": "at91-sama5d2_ptc_ek",
  "image_prefix": "openwrt-19.07.4-at91-sama5-at91-sama5d2_ptc_ek",
  "images": [
    {
      "name": "openwrt-19.07.4-at91-sama5-at91-sama5d2_ptc_ek-squashfs-zImage",
      "sha256": "8119a1afaf186bc999559df2a571fdfe00e2d0df6d9cbe8df6ab4ccba54328ff",
      "type": "zImage"
    },
    {
      "name": "openwrt-19.07.4-at91-sama5-at91-sama5d2_ptc_ek-ubifs-root.ubi",
      "sha256": "7abd2202cf2dc05380748a32684b9a47a6b8bb8292abb40b494364beed1e4dd6",
      "type": "root"
    },
    {
      "name": "openwrt-19.07.4-at91-sama5-at91-sama5d2_ptc_ek-squashfs-root.ubi",
      "sha256": "58a6ba0bbaba945b7f768e812eefdae9a6ad700088cbcc860b2ee766e03c3edd",
      "type": "root"
    },
    {
      "name": "openwrt-19.07.4-at91-sama5-at91-sama5d2_ptc_ek-ext4-sdcard.img.gz",
      "sha256": "7bc5d7ff5484ff1e857c6373aa0b25bb605c0aed1d8331d55ffa9baf4d2340bb",
      "type": "sdcard"
    },
    {
      "name": "openwrt-19.07.4-at91-sama5-at91-sama5d2_ptc_ek-ubifs-zImage",
      "sha256": "8119a1afaf186bc999559df2a571fdfe00e2d0df6d9cbe8df6ab4ccba54328ff",
      "type": "zImage"
    }
  ],
  "metadata_version": 1,
  "supported_devices": [],
  "target": "at91/sama5",
  "titles": [
    {
      "title": "Microchip(Atmel AT91) SAMA5D2 PTC Ek"
    }
  ],
  "version_code": "r11208-ce6496d796",
  "version_number": "19.07.4"
}