{
  "arch_packages": "mipsel_24kc",
  "build_at": "2020-09-16 13:55:54",
  "default_packages": [
    "base-files",
    "libc",
    "libgcc",
    "busybox",
    "dropbear",
    "mtd",
    "uci",
    "opkg",
    "netifd",
    "fstools",
    "uclient-fetch",
    "logd",
    "kmod-leds-gpio",
    "kmod-gpio-button-hotplug",
    "swconfig",
    "kmod-mt76",
    "wpad-mini",
    "dnsmasq",
    "iptables",
    "ip6tables",
    "ppp",
    "ppp-mod-pppoe",
    "firewall",
    "odhcpd-ipv6only",
    "odhcp6c",
    "kmod-ipt-offload",
    "kmod-leds-gpio",
    "kmod-gpio-button-hotplug",
    "swconfig"
  ],
  "device_packages": [
    "kmod-usb2",
    "kmod-usb-ohci",
    "kmod-usb-ledtrig-usbport",
    "kmod-sdhci-mt7620"
  ],
  "id": "vocore2",
  "image_prefix": "openwrt-18.06.9-ramips-mt76x8-vocore2",
  "images": [
    {
      "name": "openwrt-18.06.9-ramips-mt76x8-vocore2-squashfs-sysupgrade.bin",
      "sha256": "9dbe8dc0e026d508df06b7d166334c96e2744fbf139ec82eebe04359cc89e100",
      "type": "sysupgrade"
    }
  ],
  "metadata_version": 1,
  "supported_devices": [
    "vocore2"
  ],
  "target": "ramips/mt76x8",
  "titles": [
    {
      "title": "VoCore VoCore2"
    }
  ],
  "version_code": "r7989-82fbd85747",
  "version_number": "18.06.9"
}