{
  "arch_packages": "arm_cortex-a8_vfpv3",
  "build_at": "2020-12-11 11:58:51",
  "default_packages": [
    "base-files",
    "ca-bundle",
    "dropbear",
    "fstools",
    "libc",
    "libgcc",
    "libustream-wolfssl",
    "logd",
    "mtd",
    "netifd",
    "opkg",
    "uci",
    "uclient-fetch",
    "urandom-seed",
    "urngd",
    "busybox",
    "procd",
    "uboot-envtools",
    "partx-utils",
    "mkf2fs",
    "e2fsprogs",
    "dnsmasq",
    "firewall",
    "ip6tables",
    "iptables",
    "kmod-ipt-offload",
    "odhcp6c",
    "odhcpd-ipv6only",
    "ppp",
    "ppp-mod-pppoe",
    "uboot-envtools",
    "partx-utils",
    "mkf2fs",
    "e2fsprogs"
  ],
  "device_packages": ["kmod-sun4i-emac", "kmod-rtc-sunxi", "kmod-rtl8192cu"],
  "id": "linksprite_a10-pcduino",
  "image_prefix": "openwrt-sunxi-cortexa8-linksprite_a10-pcduino",
  "images": [
    {
      "name": "openwrt-sunxi-cortexa8-linksprite_a10-pcduino-squashfs-sdcard.img.gz",
      "sha256": "db7335bd13a495ddabfaadfa6b7ecc7e627dfa23b37e383b418b84c7227dd837",
      "type": "sdcard"
    },
    {
      "name": "openwrt-sunxi-cortexa8-linksprite_a10-pcduino-ext4-sdcard.img.gz",
      "sha256": "3279f759e34aad91f5f87abd0273acf0d9b7e28b64bbbe8122aa6da4b55dbe61",
      "type": "sdcard"
    }
  ],
  "metadata_version": 1,
  "source_date_epoch": "1607683657",
  "supported_devices": ["linksprite,a10-pcduino"],
  "target": "sunxi/cortexa8",
  "titles": [{ "model": "pcDuino", "vendor": "LinkSprite" }],
  "version_code": "r15183-81df645572",
  "version_number": "SNAPSHOT"
}
