{
  "arch_packages": "mipsel_24kc",
  "build_at": "2023-09-22 06:59:57",
  "default_packages": [
    "base-files",
    "busybox",
    "ca-bundle",
    "dnsmasq",
    "dropbear",
    "firewall4",
    "fstools",
    "kmod-gpio-button-hotplug",
    "kmod-leds-gpio",
    "kmod-nft-offload",
    "libc",
    "libgcc",
    "libustream-wolfssl",
    "logd",
    "mtd",
    "netifd",
    "nftables",
    "odhcp6c",
    "odhcpd-ipv6only",
    "opkg",
    "ppp",
    "ppp-mod-pppoe",
    "procd",
    "procd-seccomp",
    "procd-ujail",
    "uci",
    "uclient-fetch",
    "urandom-seed",
    "urngd",
    "wpad-basic-wolfssl"
  ],
  "device_packages": [
    "kmod-mt7603",
    "kmod-mt76x2",
    "kmod-usb3",
    "kmod-usb-ledtrig-usbport",
    "uboot-envtools"
  ],
  "image_path": "releases/22.03.5/targets/ramips/mt7621/",
  "image_prefix": "openwrt-22.03.5-ramips-mt7621-samknows_whitebox-v8",
  "images": [
    {
      "filesystem": "squashfs",
      "name": "openwrt-22.03.5-ramips-mt7621-samknows_whitebox-v8-squashfs-sysupgrade.bin",
      "sha256": "577cc6eba186dbf2db82189b8e72df44173c5f1c3fdd6b5ebe2833cc21637d75",
      "sha256_unsigned": "89744b01a73484d4777a7151dd60643d588d9ebd713a7a69b9dd05d72029069a",
      "type": "sysupgrade"
    },
    {
      "filesystem": "initramfs",
      "name": "openwrt-22.03.5-ramips-mt7621-samknows_whitebox-v8-initramfs-kernel.bin",
      "sha256": "6258561cf98c1f9d03c4309eb5f5d4b0f9a10f9651560fdc88c53fce0f746faa",
      "sha256_unsigned": "6258561cf98c1f9d03c4309eb5f5d4b0f9a10f9651560fdc88c53fce0f746faa",
      "type": "kernel"
    }
  ],
  "metadata_version": 1,
  "model_id": "samknows_whitebox-v8",
  "source_date_epoch": 1682627295,
  "supported_devices": [
    "samknows,whitebox-v8",
    "sk-wb8"
  ],
  "target": "ramips/mt7621",
  "titles": [
    {
      "model": "Whitebox 8",
      "vendor": "SamKnows"
    }
  ],
  "version_code": "r20134-5f15225c1e",
  "version_number": "22.03.5"
}