{"arch_packages":"arm_arm1176jzf-s_vfp","default_packages":["base-files","bcm27xx-gpu-fw","busybox","ca-bundle","dnsmasq","dropbear","e2fsprogs","firewall4","fstools","kmod-fs-vfat","kmod-nft-offload","kmod-nls-cp437","kmod-nls-iso8859-1","kmod-sound-arm-bcm2835","kmod-sound-core","kmod-usb-hid","libc","libgcc","libustream-mbedtls","logd","mkf2fs","mtd","netifd","nftables","odhcp6c","odhcpd-ipv6only","opkg","partx-utils","ppp","ppp-mod-pppoe","procd","procd-seccomp","procd-ujail","uci","uclient-fetch","urandom-seed"],"metadata_version":1,"profiles":{"rpi":{"device_packages":["cypress-firmware-43430-sdio","brcmfmac-nvram-43430-sdio","kmod-brcmfmac","wpad-basic-mbedtls","iwinfo"],"image_prefix":"openwrt-23.05.4-bcm27xx-bcm2708-rpi","images":[{"filesystem":"squashfs","name":"openwrt-23.05.4-bcm27xx-bcm2708-rpi-squashfs-sysupgrade.img.gz","sha256":"9d50423040ee1856a24f68bffc825d58857590e473c7359aca3cbee15ae82345","sha256_unsigned":"e4a0cccdb759dfb59382f27c4c0cf621d5bfc37af0e9f2091688b3b73154e765","type":"sysupgrade"},{"filesystem":"ext4","name":"openwrt-23.05.4-bcm27xx-bcm2708-rpi-ext4-factory.img.gz","sha256":"bdfeae5d9aa3c70be737559701d5b3fe1a805f74215d268339fd506a7e2519dc","sha256_unsigned":"bdfeae5d9aa3c70be737559701d5b3fe1a805f74215d268339fd506a7e2519dc","type":"factory"},{"filesystem":"ext4","name":"openwrt-23.05.4-bcm27xx-bcm2708-rpi-ext4-sysupgrade.img.gz","sha256":"2958b2aee0e20a012f97fa273483397f01ca32d9adb7529839449693bc2c1d4d","sha256_unsigned":"76d7b0888fcaaf233721949aece6f78870f9abb60b326a8e999da7bbbae5fef5","type":"sysupgrade"},{"filesystem":"squashfs","name":"openwrt-23.05.4-bcm27xx-bcm2708-rpi-squashfs-factory.img.gz","sha256":"edd869bd7a0de10bf301e7035ac7700aa7e025465f0b9677ef28e0e09f6b345a","sha256_unsigned":"edd869bd7a0de10bf301e7035ac7700aa7e025465f0b9677ef28e0e09f6b345a","type":"factory"}],"supported_devices":["rpi-b","rpi-b-plus","rpi-cm","rpi-zero","rpi-zero-w","raspberrypi,model-b","raspberrypi,model-b-plus","raspberrypi,model-b-rev2","raspberrypi,compute-module","raspberrypi,compute-module-1","raspberrypi,model-zero","raspberrypi,model-zero-w"],"titles":[{"model":"B/B+/CM/Zero/ZeroW","vendor":"Raspberry Pi"}]}},"source_date_epoch":1721081658,"target":"bcm27xx/bcm2708","version_code":"r24012-d8dd03c46f","version_number":"23.05.4"}