{
  "arch_packages": "aarch64_cortex-a53",
  "build_at": "2020-12-11 11:18:56",
  "default_packages": [
    "base-files",
    "ca-bundle",
    "dropbear",
    "fstools",
    "libc",
    "libgcc",
    "libustream-wolfssl",
    "logd",
    "mtd",
    "netifd",
    "opkg",
    "uci",
    "uclient-fetch",
    "urandom-seed",
    "urngd",
    "busybox",
    "procd",
    "uboot-envtools",
    "partx-utils",
    "mkf2fs",
    "e2fsprogs",
    "dnsmasq",
    "firewall",
    "ip6tables",
    "iptables",
    "kmod-ipt-offload",
    "odhcp6c",
    "odhcpd-ipv6only",
    "ppp",
    "ppp-mod-pppoe",
    "uboot-envtools",
    "partx-utils",
    "mkf2fs",
    "e2fsprogs"
  ],
  "device_packages": [],
  "id": "libretech_all-h3-cc-h5",
  "image_prefix": "openwrt-sunxi-cortexa53-libretech_all-h3-cc-h5",
  "images": [
    {
      "name": "openwrt-sunxi-cortexa53-libretech_all-h3-cc-h5-squashfs-sdcard.img.gz",
      "sha256": "6d4bbdfa3362b2a833cb222172951aec49d28eb1354357418da900a31baccb42",
      "type": "sdcard"
    },
    {
      "name": "openwrt-sunxi-cortexa53-libretech_all-h3-cc-h5-ext4-sdcard.img.gz",
      "sha256": "77caea605489ee321174d09ebf9c1e7190d04d4ecd747d92c038332a049289af",
      "type": "sdcard"
    }
  ],
  "metadata_version": 1,
  "source_date_epoch": "1607628831",
  "supported_devices": ["libretech,all-h3-cc-h5"],
  "target": "sunxi/cortexa53",
  "titles": [
    { "model": "ALL-H3-CC", "variant": "H5", "vendor": "Libre Computer" }
  ],
  "version_code": "r15182-8663072854",
  "version_number": "SNAPSHOT"
}
